NeoModel/NeoModel.py
NeoModel/__init__.py
SuniMachina/SuniMachina.py
SuniMachina/__init__.py
sunimachina/__init__.py
sunimachina/sunimachina.py
sunimachina-1.0.4.dist-info/METADATA
sunimachina-1.0.4.dist-info/WHEEL
sunimachina-1.0.4.dist-info/top_level.txt
sunimachina-1.0.4.dist-info/RECORD
