Metadata-Version: 2.1
Name: sunimachina
Version: 1.0.4
Summary: A Machine learning library
Home-page: UNKNOWN
Author: sidharth
Author-email: sidharthss2690@gmail.com
License: UNKNOWN
Platform: UNKNOWN
Requires-Dist: matplotlib
Requires-Dist: numpy
Requires-Dist: scikit-learn
Requires-Dist: scipy
